[
  {
    "id": 1,
    "title": "menu.items.sweetPotatoFries.title",
    "description": "menu.items.sweetPotatoFries.description",
    "price": 70,
    "image": "/src/assets/sweet-potato-fries.png",
    "category": "menu.categories.appetizers",
    "subcategory": "",
    "cuisine": "menu.cuisines.american",
    "rating": 3
  },
  {
    "id": 2,
    "title": "menu.items.hummusVeggiePlatter.title",
    "description": "menu.items.hummusVeggiePlatter.description",
    "price": 80,
    "image": "/src/assets/hummus.png",
    "category": "menu.categories.appetizers",
    "subcategory": "",
    "cuisine": "menu.cuisines.mediterranean",
    "rating": 4
  },
  {
    "id": 3,
    "title": "menu.items.stuffedMushrooms.title",
    "description": "menu.items.stuffedMushrooms.description",
    "price": 90,
    "image": "/src/assets/stuffed-mushroom.png",
    "category": "menu.categories.appetizers",
    "subcategory": "menu.subcategories.value",
    "cuisine": "menu.cuisines.italian",
    "rating": 4
  },
  {
    "id": 4,
    "title": "menu.items.avocadoBruschetta.title",
    "description": "menu.items.avocadoBruschetta.description",
    "price": 75,
    "image": "/src/assets/avocado.png",
    "category": "menu.categories.appetizers",
    "subcategory": "",
    "cuisine": "menu.cuisines.italian",
    "rating": 5
  },
  {
    "id": 5,
    "title": "menu.items.bakedZucchiniSticks.title",
    "description": "menu.items.bakedZucchiniSticks.description",
    "price": 85,
    "image": "/src/assets/baked-zucchini-sticks.png",
    "category": "menu.categories.appetizers",
    "subcategory": "",
    "cuisine": "menu.cuisines.italian",
    "rating": 3
  },
  {
    "id": 6,
    "title": "menu.items.falafelBalls.title",
    "description": "menu.items.falafelBalls.description",
    "price": 75,
    "image": "/src/assets/falafel-balls.png",
    "category": "menu.categories.appetizers",
    "subcategory": "",
    "cuisine": "menu.cuisines.middleEastern",
    "rating": 4
  },
  {
    "id": 7,
    "title": "menu.items.grilledChickenCaesarSalad.title",
    "description": "menu.items.grilledChickenCaesarSalad.description",
    "price": 150,
    "image": "/src/assets/chicken-salad.png",
    "category": "menu.categories.salads",
    "subcategory": "menu.subcategories.top",
    "cuisine": "menu.cuisines.american",
    "rating": 5
  },
  {
    "id": 8,
    "title": "menu.items.quinoaAvocadoSalad.title",
    "description": "menu.items.quinoaAvocadoSalad.description",
    "price": 120,
    "image": "/src/assets/quinoa.png",
    "category": "menu.categories.salads",
    "subcategory": "menu.subcategories.value",
    "cuisine": "menu.cuisines.mexican",
    "rating": 4
  },
  {
    "id": 9,
    "title": "menu.items.kaleAppleSalad.title",
    "description": "menu.items.kaleAppleSalad.description",
    "price": 110,
    "image": "/src/assets/kale-apple-salad.png",
    "category": "menu.categories.salads",
    "subcategory": "",
    "cuisine": "menu.cuisines.american",
    "rating": 3
  },
  {
    "id": 10,
    "title": "menu.items.greekSalad.title",
    "description": "menu.items.greekSalad.description",
    "price": 100,
    "image": "/src/assets/greek-salad.png",
    "category": "menu.categories.salads",
    "subcategory": "menu.subcategories.value",
    "cuisine": "menu.cuisines.greek",
    "rating": 4
  },
  {
    "id": 11,
    "title": "menu.items.spinachBerrySalad.title",
    "description": "menu.items.spinachBerrySalad.description",
    "price": 130,
    "image": "/src/assets/spinach-berry-salad.png",
    "category": "menu.categories.salads",
    "subcategory": "",
    "cuisine": "menu.cuisines.american",
    "rating": 4
  },
  {
    "id": 12,
    "title": "menu.items.chickpeaAvocadoSalad.title",
    "description": "menu.items.chickpeaAvocadoSalad.description",
    "price": 115,
    "image": "/src/assets/chickpea-avocado-salad.png",
    "category": "menu.categories.salads",
    "subcategory": "",
    "cuisine": "menu.cuisines.mediterranean",
    "rating": 3
  },
  {
    "id": 13,
    "title": "menu.items.citrusArugulaSalad.title",
    "description": "menu.items.citrusArugulaSalad.description",
    "price": 105,
    "image": "/src/assets/citrus-arugula-salad.png",
    "category": "menu.categories.salads",
    "subcategory": "",
    "cuisine": "menu.cuisines.mediterranean",
    "rating": 4
  },
  {
    "id": 14,
    "title": "menu.items.warmQuinoaKaleSalad.title",
    "description": "menu.items.warmQuinoaKaleSalad.description",
    "price": 140,
    "image": "/src/assets/warm-quinoa-kale-salad.png",
    "category": "menu.categories.salads",
    "subcategory": "menu.subcategories.value",
    "cuisine": "menu.cuisines.american",
    "rating": 4
  },
  {
    "id": 31,
    "title": "menu.items.veganSaladSmoothieDeal.title",
    "description": "menu.items.veganSaladSmoothieDeal.description",
    "price": 90,
    "image": "/src/assets/vegan-salad-smoothie-deal.png",
    "category": "menu.categories.salads",
    "subcategory": "menu.subcategories.offers",
    "cuisine": "menu.cuisines.vegan",
    "rating": 4
  },
  {
    "id": 15,
    "title": "menu.items.grilledSalmonWithVeggies.title",
    "description": "menu.items.grilledSalmonWithVeggies.description",
    "price": 200,
    "image": "/src/assets/grilled-salmon-veggies.png",
    "category": "menu.categories.main",
    "subcategory": "menu.subcategories.top",
    "cuisine": "menu.cuisines.american",
    "rating": 5
  },
  {
    "id": 16,
    "title": "menu.items.grilledTofuStirFry.title",
    "description": "menu.items.grilledTofuStirFry.description",
    "price": 150,
    "image": "/src/assets/grilled-tofu-stir-fry.png",
    "category": "menu.categories.main",
    "subcategory": "menu.subcategories.top",
    "cuisine": "menu.cuisines.asian",
    "rating": 5
  },
  {
    "id": 17,
    "title": "menu.items.chickenStirFry.title",
    "description": "menu.items.chickenStirFry.description",
    "price": 160,
    "image": "/src/assets/stir-fry.png",
    "category": "menu.categories.main",
    "subcategory": "menu.subcategories.top",
    "cuisine": "menu.cuisines.asian",
    "rating": 5
  },
  {
    "id": 18,
    "title": "menu.items.zucchiniNoodlesWithPesto.title",
    "description": "menu.items.zucchiniNoodlesWithPesto.description",
    "price": 150,
    "image": "/src/assets/zucchini-noodles-pesto.png",
    "category": "menu.categories.main",
    "subcategory": "menu.subcategories.value",
    "cuisine": "menu.cuisines.italian",
    "rating": 4
  },
  {
    "id": 19,
    "title": "menu.items.lentilStew.title",
    "description": "menu.items.lentilStew.description",
    "price": 140,
    "image": "/src/assets/lentil-stew.png",
    "category": "menu.categories.main",
    "subcategory": "",
    "cuisine": "menu.cuisines.middleEastern",
    "rating": 4
  },
  {
    "id": 20,
    "title": "menu.items.turkeyLettuceSandwich.title",
    "description": "menu.items.turkeyLettuceSandwich.description",
    "price": 130,
    "image": "/src/assets/turkey-lettuce-sandwich.png",
    "category": "menu.categories.main",
    "subcategory": "",
    "cuisine": "menu.cuisines.american",
    "rating": 4
  },
  {
    "id": 21,
    "title": "menu.items.grilledTofuSkewers.title",
    "description": "menu.items.grilledTofuSkewers.description",
    "price": 145,
    "image": "/src/assets/tofu-skewers.png",
    "category": "menu.categories.main",
    "subcategory": "",
    "cuisine": "menu.cuisines.mediterranean",
    "rating": 3
  },
  {
    "id": 22,
    "title": "menu.items.eggplantParmesan.title",
    "description": "menu.items.eggplantParmesan.description",
    "price": 170,
    "image": "/src/assets/eggplant-parmesan.png",
    "category": "menu.categories.main",
    "subcategory": "menu.subcategories.top",
    "cuisine": "menu.cuisines.italian",
    "rating": 5
  },
  {
    "id": 23,
    "title": "menu.items.beefBroccoliStirFry.title",
    "description": "menu.items.beefBroccoliStirFry.description",
    "price": 180,
    "image": "/src/assets/beef-broccoli-stir-fry.png",
    "category": "menu.categories.main",
    "subcategory": "menu.subcategories.value",
    "cuisine": "menu.cuisines.asian",
    "rating": 4
  },
  {
    "id": 24,
    "title": "menu.items.burritoBowl.title",
    "description": "menu.items.burritoBowl.description",
    "price": 155,
    "image": "/src/assets/burrito-bowl.png",
    "category": "menu.categories.main",
    "subcategory": "",
    "cuisine": "menu.cuisines.mexican",
    "rating": 3
  },
  {
    "id": 25,
    "title": "menu.items.lambShawarmaPlate.title",
    "description": "menu.items.lambShawarmaPlate.description",
    "price": 200,
    "image": "/src/assets/lamb-shawarma.png",
    "category": "menu.categories.main",
    "subcategory": "menu.subcategories.top",
    "cuisine": "menu.cuisines.middleEastern",
    "rating": 5
  },
  {
    "id": 30,
    "title": "menu.items.chickenWrapCombo.title",
    "description": "menu.items.chickenWrapCombo.description",
    "price": 110,
    "image": "/src/assets/chicken-wrap-combo.png",
    "category": "menu.categories.main",
    "subcategory": "menu.subcategories.offers",
    "cuisine": "menu.cuisines.mediterranean",
    "rating": 5
  },
  {
    "id": 32,
    "title": "menu.items.grilledSalmonPowerPlate.title",
    "description": "menu.items.grilledSalmonPowerPlate.description",
    "price": 130,
    "image": "/src/assets/grilled-salmon-power-plate.png",
    "category": "menu.categories.main",
    "subcategory": "menu.subcategories.offers",
    "cuisine": "menu.cuisines.nordic",
    "rating": 5
  },
  {
    "id": 26,
    "title": "menu.items.chiaPudding.title",
    "description": "menu.items.chiaPudding.description",
    "price": 80,
    "image": "/src/assets/chia-pudding.png",
    "category": "menu.categories.desserts",
    "subcategory": "",
    "cuisine": "menu.cuisines.vegan",
    "rating": 4
  },
  {
    "id": 27,
    "title": "menu.items.fruitSaladWithHoney.title",
    "description": "menu.items.fruitSaladWithHoney.description",
    "price": 70,
    "image": "/src/assets/fruit-salad-honey.png",
    "category": "menu.categories.desserts",
    "subcategory": "",
    "cuisine": "menu.cuisines.mediterranean",
    "rating": 4
  },
  {
    "id": 28,
    "title": "menu.items.bananaOatCookies.title",
    "description": "menu.items.bananaOatCookies.description",
    "price": 60,
    "image": "/src/assets/banana-oat-cookies.png",
    "category": "menu.categories.desserts",
    "subcategory": "",
    "cuisine": "menu.cuisines.vegan",
    "rating": 5
  },
  {
    "id": 29,
    "title": "menu.items.avocadoBrownies.title",
    "description": "menu.items.avocadoBrownies.description",
    "price": 100,
    "image": "/src/assets/avocado-brownies.png",
    "category": "menu.categories.desserts",
    "subcategory": "menu.subcategories.top",
    "cuisine": "menu.cuisines.american",
    "rating": 5
  }      
]
